encodings.v
// OPCODES
`define LUI_OPCODE 7'b0110111
`define AUIPC_OPCODE 7'b0010111
`define JAL_OPCODE 7'b1101111
`define JALR_OPCODE 7'b1100111
`define B_TYPE_OPCODE 7'b1100011
`define LOAD_OPCODE 7'b0000011
`define STORE_OPCODE 7'b0100011
`define I_TYPE_OPCODE 7'b0010011
`define R_TYPE_OPCODE 7'b0110011

// OP1SEL
`define DATA1 1'b0
`define PC 1'b1

// OP2SEL
`define DATA2 1'b0
`define IMM 1'b1

// REG_WRITE_EN
`define REG_WRITE_EN_0 1'b0
`define REG_WRITE_EN_1 1'b1

// WB_SEL
`define ALU 2'b00
`define MEM 2'b01
`define IMM_WB 2'b10
`define PC_4 2'b11

// ALU_OP -> alu.v
`define ADD 5'b00000
`define SUB 5'b00010
`define SLL 5'b00100
`define SLT 5'b01000
`define SLTU 5'b01100
`define XOR 5'b10000
`define SRL 5'b10100
`define SRA 5'b10110
`define OR 5'b11000
`define AND 5'b11100
`define MUL 5'b00001
`define MULH 5'b00101
`define MULHSU 5'b01001
`define MULHU 5'b01101
`define DIV 5'b10001
`define DIVU 5'b10101
`define REM 5'b11001
`define REMU 5'b11101

// BRANCH_JUMP
`define BEQ 3'b000
`define BNE 3'b001
`define NO 3'b010
`define J 3'b011
`define BLT 3'b100
`define BGE 3'b101
`define BLTU 3'b110
`define BGEU 3'b111

// IMM_SEL -> immediate_generate.v
`define U_TYPE 3'b000
`define J_TYPE 3'b001
`define S_TYPE 3'b010
`define B_TYPE 3'b011
`define I_SIGNED_TYPE 3'b100
`define I_SHIFT_TYPE 3'b101
`define I_UNSIGNED_TYPE 3'b111

// MEM_RW
`define NO_RW 4'b0000
`define LB 4'b1000
`define LH 4'b1001
`define LW 4'b1010
`define LBU 4'b1100
`define LHU 4'b1101
`define SB 4'b1011
`define SH 4'b1110
`define SW 4'b1111

alu_module/alu.v
`include "../utils/encodings.v"

module alu (DATA1, DATA2, RESULT, SELECT);

    // port declaration
    input [31:0] DATA1, DATA2;
    input [4:0] SELECT;     // func3: 3bits + func7[5] + func7[0]
    output reg [31:0] RESULT;
    

    // alu intermediate results
    wire [31:0] ADD_RESULT,
                SUB_RESULT,
                SLL_RESULT,
                SLT_RESULT,
                SLTU_RESULT,
                XOR_RESULT,
                SRL_RESULT,
                SRA_RESULT,
                OR_RESULT,
                AND_RESULT,
                DIV_RESULT,
                DIVU_RESULT,
                REM_RESULT,
                REMU_RESULT;
    
    wire [63:0] MUL_RESULT,
                MULHSU_RESULT,
                MULHU_RESULT;

    //  --> should add proper delays 
    assign ADD_RESULT = DATA1 + DATA2;       // addition
    assign SUB_RESULT = DATA1 - DATA2;       // subtraction

    assign SLT_RESULT = ($signed(DATA1) < $signed(DATA2)) ? 1'b1 : 1'b0;         // set less than
    assign SLTU_RESULT = ($unsigned(DATA1) < $unsigned(DATA2)) ? 1'b1 : 1'b0;    // set less than unsigned
    
    assign AND_RESULT = DATA1 & DATA2;       // bitwise logical AND
    assign OR_RESULT = DATA1 | DATA2;        // bitwise logical OR
    assign XOR_RESULT = DATA1 ^ DATA2;       // bitwise logical XOR
    assign SLL_RESULT = DATA1 << DATA2;      // Logical Left Shift
    assign SRL_RESULT = DATA1 >> DATA2;      // Logical Right Shift
    assign SRA_RESULT = DATA1 >>> DATA2;     // Arithmetic Right shift
    
    // --> upper 32 bit
    assign MUL_RESULT = $signed(DATA1) * $signed(DATA2);       // Multiplication High Signed x Signed
    assign MULHU_RESULT = $unsigned(DATA1) * $unsigned(DATA2); // Multiplication High Unsigned x Unsigned
    assign MULHSU_RESULT = $signed(DATA1) * $unsigned(DATA2);  // Multiplication High Signed x UnSigned
    
    // DIV --> should round towards zero 
    assign DIV_RESULT = $signed(DATA1) / $signed(DATA2);       // Division
    assign DIVU_RESULT = $unsigned(DATA1) / $unsigned(DATA2);  // Division Unsigned
    assign REM_RESULT = $signed(DATA1) % $signed(DATA2);       // Remainder
    assign REMU_RESULT = $unsigned(DATA1) % $unsigned(DATA2);  // Remainder Unsigned

    always @(SELECT or ADD_RESULT or SUB_RESULT or SLL_RESULT or SLT_RESULT or 
             SLTU_RESULT or XOR_RESULT or SRL_RESULT or SRA_RESULT or OR_RESULT or 
             AND_RESULT or MUL_RESULT or MULHSU_RESULT or MULHU_RESULT or
             DIV_RESULT or DIVU_RESULT or REM_RESULT or REMU_RESULT)
    begin
        case (SELECT)
            `ADD: RESULT = ADD_RESULT; 
            `SUB: RESULT = SUB_RESULT; 
            `SLL: RESULT = SLL_RESULT; 
            `SLT: RESULT = SLT_RESULT; 
            `SLTU: RESULT = SLTU_RESULT; 
            `XOR: RESULT = XOR_RESULT; 
            `SRL: RESULT = SRL_RESULT; 
            `SRA: RESULT = SRA_RESULT; 
            `OR: RESULT = OR_RESULT; 
            `AND: RESULT = AND_RESULT; 
            `MUL: RESULT = MUL_RESULT[31:0];
            `MULH: RESULT = MUL_RESULT[63:32]; 
            `MULHSU: RESULT = MULHSU_RESULT[63:32]; 
            `MULHU: RESULT = MULHU_RESULT[63:32]; 
            `DIV: RESULT = DIV_RESULT; 
            `DIVU: RESULT = DIVU_RESULT; 
            `REM : RESULT = REM_RESULT; 
            `REMU: RESULT = REMU_RESULT; 
                
            default:  RESULT = 0 ;  
                                
        endcase
    end

endmodule

alu_module/alu_tb.v
`include "../utils/macros.v"
`include "../utils/encodings.v"
`include "alu.v"

module alu_tb;

    reg [31:0] DATA1, DATA2;
    reg [4:0] SELECT;
    wire [31:0] RESULT;

    alu myalu (DATA1, DATA2, RESULT, SELECT);
    
    initial begin
        $dumpfile("alu_wavedata.vcd");
        $dumpvars(0, alu_tb);

        #1;
            SELECT = `ADD;
            DATA1 = 32'b10000100000000000000000000000000;
            DATA2 = 32'd2;
        #5
            `assert(RESULT, 32'b10000100000000000000000000000010);
            $display("ALU-OP ADD Passed!");
    
            SELECT = `SUB;
        #5
            `assert(RESULT, -32'd2080374786);
            $display("ALU-OP SUB Passed!");
            
            SELECT = `SLL;
        #5
            `assert(RESULT, 32'b00010000000000000000000000000000);
            $display("ALU-OP SLL Passed!");
        
            SELECT = `XOR;
        #5
            `assert(RESULT, 32'b10000100000000000000000000000010);
            $display("ALU-OP XOR Passed!");
        
            SELECT = `SRL;
        #5
            `assert(RESULT, 32'b00100001000000000000000000000000);
            $display("ALU-OP SRL Passed!");
        
            SELECT = `SRA;
        #5  
            `assert(RESULT, 32'b00100001000000000000000000000000); //expect: 11100001000000000000000000000000
        
            SELECT = `OR;
        #5  
            `assert(RESULT, 32'b10000100000000000000000000000010);
            $display("ALU-OP OR Passed!");
        
            SELECT = `MUL;
        #5  
            `assert(RESULT, 32'b00001000000000000000000000000000);
            $display("ALU-OP MUL Passed!");
        
            SELECT = `MULH;
        #5  
            `assert(RESULT, 32'b11111111111111111111111111111111);
            $display("ALU-OP MULH Passed!");
        
            SELECT = `MULHU;
        #5  
            `assert(RESULT, 32'b00000000000000000000000000000001);
            $display("ALU-OP MULHU Passed!");
        
            SELECT = `MULHSU;
        #5  
            `assert(RESULT, 32'b00000000000000000000000000000001); //unsigned???
            $display("ALU-OP MULHSU Passed!");
        
            SELECT = `DIV;
        #5  
            `assert(RESULT, 32'b11000010000000000000000000000000);
            $display("ALU-OP DIV Passed!");
        
            SELECT = `DIVU;
        #5  
            `assert(RESULT, 32'b01000010000000000000000000000000);
            $display("ALU-OP DIVU Passed!");
        
            SELECT = `REMU;
        #5  
            `assert(RESULT, 32'd0);
            $display("ALU-OP REMU Passed!");

        #500
        $finish;
    end

endmodule

alu_module/alu_wavedata.vcd
$date
	Thu Sep  5 23:58:12 2024
$end
$version
	Icarus Verilog
$end
$timescale
	1s
$end
$scope module alu_tb $end
$var wire 32 ! RESULT [31:0] $end
$var reg 32 " DATA1 [31:0] $end
$var reg 32 # DATA2 [31:0] $end
$var reg 5 $ SELECT [4:0] $end
$scope module myalu $end
$var wire 32 % AND_RESULT [31:0] $end
$var wire 32 & DATA1 [31:0] $end
$var wire 32 ' DATA2 [31:0] $end
$var wire 32 ( OR_RESULT [31:0] $end
$var wire 5 ) SELECT [4:0] $end
$var wire 32 * XOR_RESULT [31:0] $end
$var wire 32 + SUB_RESULT [31:0] $end
$var wire 32 , SRL_RESULT [31:0] $end
$var wire 32 - SRA_RESULT [31:0] $end
$var wire 32 . SLT_RESULT [31:0] $end
$var wire 32 / SLTU_RESULT [31:0] $end
$var wire 32 0 SLL_RESULT [31:0] $end
$var wire 32 1 REM_RESULT [31:0] $end
$var wire 32 2 REMU_RESULT [31:0] $end
$var wire 64 3 MUL_RESULT [63:0] $end
$var wire 64 4 MULHU_RESULT [63:0] $end
$var wire 64 5 MULHSU_RESULT [63:0] $end
$var wire 32 6 DIV_RESULT [31:0] $end
$var wire 32 7 DIVU_RESULT [31:0] $end
$var wire 32 8 ADD_RESULT [31:0] $end
$var reg 32 9 RESULT [31:0] $end
$upscope $end
$upscope $end
$enddefinitions $end
$comment Show the parameter values. $end
$dumpall
$end
#0
$dumpvars
b0 9
bx 8
bx 7
bx 6
bx 5
bx 4
bx 3
bx 2
bx 1
bx 0
b0x /
b0x .
bx -
bx ,
bx +
bx *
bx )
bx (
bx '
bx &
bx %
bx $
bx #
bx "
b0 !
$end
#1
b1 .
b0 /
b100001000000000000000000000000000 4
b100001000000000000000000000000000 5
b0 %
b10000100000000000000000000000010 (
b10000100000000000000000000000010 *
b10000100000000000000000000000010 !
b10000100000000000000000000000010 9
b10000100000000000000000000000010 8
b10000011111111111111111111111110 +
b10000000000000000000000000000 0
b100001000000000000000000000000 ,
b100001000000000000000000000000 -
b1111111111111111111111111111111100001000000000000000000000000000 3
b11000010000000000000000000000000 6
b1000010000000000000000000000000 7
b0 1
b0 2
b10 #
b10 '
b10000100000000000000000000000000 "
b10000100000000000000000000000000 &
b0 $
b0 )
#6
b10000011111111111111111111111110 !
b10000011111111111111111111111110 9
b10 $
b10 )
#11
b10000000000000000000000000000 !
b10000000000000000000000000000 9
b100 $
b100 )
#16
b10000100000000000000000000000010 !
b10000100000000000000000000000010 9
b10000 $
b10000 )
#21
b100001000000000000000000000000 !
b100001000000000000000000000000 9
b10100 $
b10100 )
#26
b10110 $
b10110 )
#31
b10000100000000000000000000000010 !
b10000100000000000000000000000010 9
b11000 $
b11000 )
#36
b1000000000000000000000000000 !
b1000000000000000000000000000 9
b1 $
b1 )
#41
b11111111111111111111111111111111 !
b11111111111111111111111111111111 9
b101 $
b101 )
#46
b1 !
b1 9
b1101 $
b1101 )
#51
b1001 $
b1001 )
#56
b11000010000000000000000000000000 !
b11000010000000000000000000000000 9
b10001 $
b10001 )
#61
b1000010000000000000000000000000 !
b1000010000000000000000000000000 9
b10101 $
b10101 )
#66
b0 !
b0 9
b11101 $
b11101 )
