data_memory_module/data_memory.v
module data_memory (CLK, RESET, READ_WRITE_EN, ADDRESS, WRITEDATA, READDATA);

input				CLK;
input           	RESET;
input [3:0]         READ_WRITE_EN;  
input [31:0]      	ADDRESS;
input [31:0]     	WRITEDATA;
output reg [31:0]	READDATA;

//Declare memory array 524288x8-bits
//512kByte
reg [7:0] MEM_ARRAY [524287:0];

wire [31:0] LW;
wire [15:0] LH;
wire [7:0] LB;
wire LOAD_BYTE, LOAD_HALF, LOAD_WORD, LOAD_BYTE_U, LOAD_HALF_U, LOAD;

assign LW = {MEM_ARRAY[ADDRESS+3], MEM_ARRAY[ADDRESS+2], MEM_ARRAY[ADDRESS+1], MEM_ARRAY[ADDRESS]};
assign LH = {MEM_ARRAY[ADDRESS+1], MEM_ARRAY[ADDRESS]};
assign LB = MEM_ARRAY[ADDRESS];

assign LOAD_BYTE = READ_WRITE_EN[3] & !READ_WRITE_EN[2] & !READ_WRITE_EN[1] & !READ_WRITE_EN[0];
assign LOAD_HALF = READ_WRITE_EN[3] & !READ_WRITE_EN[2] & !READ_WRITE_EN[1] & READ_WRITE_EN[0];
assign LOAD_WORD = READ_WRITE_EN[3] & !READ_WRITE_EN[2] & READ_WRITE_EN[1] & !READ_WRITE_EN[0];
assign LOAD_BYTE_U = READ_WRITE_EN[3] & READ_WRITE_EN[2] & !READ_WRITE_EN[1] & !READ_WRITE_EN[0];
assign LOAD_HALF_U = READ_WRITE_EN[3] & READ_WRITE_EN[2] & !READ_WRITE_EN[1] & READ_WRITE_EN[0];
assign LOAD = LOAD_BYTE | LOAD_HALF | LOAD_WORD | LOAD_BYTE_U | LOAD_HALF_U;

//Read
always @(posedge CLK)
begin
	if (~LOAD) READDATA <= 32'b0;
	else begin
		case (READ_WRITE_EN[2:0])
		3'b000: READDATA <= {{24{LB[7]}},LB};
		3'b001: READDATA <= {{16{LH[15]}},LH};
		3'b010: READDATA <= LW;
		3'b100: READDATA <= {{24{1'b0}},LB};
		3'b101: READDATA <= {{16{1'b0}},LH};
		endcase
	end
end

//Write
always @(posedge CLK)
begin
	if (READ_WRITE_EN[3]) begin
		case (READ_WRITE_EN[2:0])
		3'b011: MEM_ARRAY[ADDRESS] <= WRITEDATA[7:0];
		3'b110: {MEM_ARRAY[ADDRESS+1], MEM_ARRAY[ADDRESS]} <= WRITEDATA[15:0];
		3'b111: {MEM_ARRAY[ADDRESS+3], MEM_ARRAY[ADDRESS+2], MEM_ARRAY[ADDRESS+1], MEM_ARRAY[ADDRESS]} <= WRITEDATA;
	    endcase
	end
end

//Reset memory
integer i;

always @(posedge CLK or posedge RESET)
begin
    if (RESET)
    begin
        for (i = 0; i < 524288; i = i + 1)
            MEM_ARRAY[i] <= 8'b0;
    end
end

endmodule

data_memory_module/data_memory_tb.v
`include "data_memory.v"

module data_memory_tb();

    reg CLK, RESET;
    reg [3:0] READ_WRITE_EN;
    reg [31:0] ADDRESS;
    reg [31:0] WRITEDATA;
    wire [31:0] READDATA;

    integer j;
    
    data_memory my_data_memory (
    .CLK (CLK), 
    .RESET (RESET), 
    .READ_WRITE_EN (READ_WRITE_EN), 
    .ADDRESS (ADDRESS), 
    .WRITEDATA (WRITEDATA), 
    .READDATA (READDATA)    
);

    initial begin
        $dumpfile("data_memory_wavedata.vcd");
        $dumpvars(0, data_memory_tb);
        for(j = 0; j < 100; j = j + 1) $dumpvars(0, my_data_memory.MEM_ARRAY[j]);

        CLK = 1'b0;
        RESET = 1'b0;

        READ_WRITE_EN = 4'b1111;
        ADDRESS = 32'h00000000;
        WRITEDATA = 32'h1234ABCD;
        
        #5;
        RESET = 1'b1;
        #4;
        RESET = 1'b0;
        
        #10;
        READ_WRITE_EN = 4'b1010;
        ADDRESS = 32'h00000004;
        WRITEDATA = 32'hABCD1235;

        #10;
        READ_WRITE_EN = 4'b1010;
        ADDRESS = 32'h00000000;
        WRITEDATA = 32'hABCD1236;

        #10;
        READ_WRITE_EN = 4'b1000;
        ADDRESS = 32'h00000000;
        WRITEDATA = 32'hABCD1233;

        #10;
        READ_WRITE_EN = 4'b1101;
        ADDRESS = 32'h00000000;
        WRITEDATA = 32'hABCD1224;

        #10;
        READ_WRITE_EN = 4'b1110;
        ADDRESS = 32'h00000004;
        WRITEDATA = 32'h32341234;

        #10;
        READ_WRITE_EN = 4'b1111;
        ADDRESS = 32'h00000008;
        WRITEDATA = 32'h32341234;

        #10;
        READ_WRITE_EN = 4'b1100;
        ADDRESS = 32'h00000008;
        WRITEDATA = 32'h32331234;

        #500;
        $finish;
    end

    // clock genaration.
    always begin
        #4 CLK = ~CLK;
    end

endmodule

data_memory_module/data_memory_wavedata.vcd
$date
	Fri Sep 20 23:11:33 2024
$end
$version
	Icarus Verilog
$end
$timescale
	1s
$end
$scope module data_memory_tb $end
$var wire 32 ! READDATA [31:0] $end
$var reg 32 " ADDRESS [31:0] $end
$var reg 1 # CLK $end
$var reg 4 $ READ_WRITE_EN [3:0] $end
$var reg 1 % RESET $end
$var reg 32 & WRITEDATA [31:0] $end
$var integer 32 ' j [31:0] $end
$scope module my_data_memory $end
$var wire 32 ( ADDRESS [31:0] $end
$var wire 1 # CLK $end
$var wire 8 ) LB [7:0] $end
$var wire 1 * LOAD $end
$var wire 1 + LOAD_BYTE $end
$var wire 1 , LOAD_BYTE_U $end
$var wire 1 - LOAD_HALF $end
$var wire 1 . LOAD_HALF_U $end
$var wire 1 / LOAD_WORD $end
$var wire 4 0 READ_WRITE_EN [3:0] $end
$var wire 1 % RESET $end
$var wire 32 1 WRITEDATA [31:0] $end
$var wire 32 2 LW [31:0] $end
$var wire 16 3 LH [15:0] $end
$var reg 32 4 READDATA [31:0] $end
$var integer 32 5 i [31:0] $end
$upscope $end
$upscope $end
$scope module data_memory_tb $end
$scope module my_data_memory $end
$var reg 8 6 \MEM_ARRAY[0] [7:0] $end
$upscope $end
$upscope $end
$scope module data_memory_tb $end
$scope module my_data_memory $end
$var reg 8 7 \MEM_ARRAY[1] [7:0] $end
$upscope $end
$upscope $end
$scope module data_memory_tb $end
$scope module my_data_memory $end
$var reg 8 8 \MEM_ARRAY[2] [7:0] $end
$upscope $end
$upscope $end
$scope module data_memory_tb $end
$scope module my_data_memory $end
$var reg 8 9 \MEM_ARRAY[3] [7:0] $end
$upscope $end
$upscope $end
$scope module data_memory_tb $end
$scope module my_data_memory $end
$var reg 8 : \MEM_ARRAY[4] [7:0] $end
$upscope $end
$upscope $end
$scope module data_memory_tb $end
$scope module my_data_memory $end
$var reg 8 ; \MEM_ARRAY[5] [7:0] $end
$upscope $end
$upscope $end
$scope module data_memory_tb $end
$scope module my_data_memory $end
$var reg 8 < \MEM_ARRAY[6] [7:0] $end
$upscope $end
$upscope $end
$scope module data_memory_tb $end
$scope module my_data_memory $end
$var reg 8 = \MEM_ARRAY[7] [7:0] $end
$upscope $end
$upscope $end
$scope module data_memory_tb $end
$scope module my_data_memory $end
$var reg 8 > \MEM_ARRAY[8] [7:0] $end
$upscope $end
$upscope $end
$scope module data_memory_tb $end
$scope module my_data_memory $end
$var reg 8 ? \MEM_ARRAY[9] [7:0] $end
$upscope $end
$upscope $end
$scope module data_memory_tb $end
$scope module my_data_memory $end
$var reg 8 @ \MEM_ARRAY[10] [7:0] $end
$upscope $end
$upscope $end
$scope module data_memory_tb $end
$scope module my_data_memory $end
$var reg 8 A \MEM_ARRAY[11] [7:0] $end
$upscope $end
$upscope $end
$scope module data_memory_tb $end
$scope module my_data_memory $end
$var reg 8 B \MEM_ARRAY[12] [7:0] $end
$upscope $end
$upscope $end
$scope module data_memory_tb $end
$scope module my_data_memory $end
$var reg 8 C \MEM_ARRAY[13] [7:0] $end
$upscope $end
$upscope $end
$scope module data_memory_tb $end
$scope module my_data_memory $end
$var reg 8 D \MEM_ARRAY[14] [7:0] $end
$upscope $end
$upscope $end
$scope module data_memory_tb $end
$scope module my_data_memory $end
$var reg 8 E \MEM_ARRAY[15] [7:0] $end
$upscope $end
$upscope $end
$scope module data_memory_tb $end
$scope module my_data_memory $end
$var reg 8 F \MEM_ARRAY[16] [7:0] $end
$upscope $end
$upscope $end
$scope module data_memory_tb $end
$scope module my_data_memory $end
$var reg 8 G \MEM_ARRAY[17] [7:0] $end
$upscope $end
$upscope $end
$scope module data_memory_tb $end
$scope module my_data_memory $end
$var reg 8 H \MEM_ARRAY[18] [7:0] $end
$upscope $end
$upscope $end
$scope module data_memory_tb $end
$scope module my_data_memory $end
$var reg 8 I \MEM_ARRAY[19] [7:0] $end
$upscope $end
$upscope $end
$scope module data_memory_tb $end
$scope module my_data_memory $end
$var reg 8 J \MEM_ARRAY[20] [7:0] $end
$upscope $end
$upscope $end
$scope module data_memory_tb $end
$scope module my_data_memory $end
$var reg 8 K \MEM_ARRAY[21] [7:0] $end
$upscope $end
$upscope $end
$scope module data_memory_tb $end
$scope module my_data_memory $end
$var reg 8 L \MEM_ARRAY[22] [7:0] $end
$upscope $end
$upscope $end
$scope module data_memory_tb $end
$scope module my_data_memory $end
$var reg 8 M \MEM_ARRAY[23] [7:0] $end
$upscope $end
$upscope $end
$scope module data_memory_tb $end
$scope module my_data_memory $end
$var reg 8 N \MEM_ARRAY[24] [7:0] $end
$upscope $end
$upscope $end
$scope module data_memory_tb $end
$scope module my_data_memory $end
$var reg 8 O \MEM_ARRAY[25] [7:0] $end
$upscope $end
$upscope $end
$scope module data_memory_tb $end
$scope module my_data_memory $end
$var reg 8 P \MEM_ARRAY[26] [7:0] $end
$upscope $end
$upscope $end
$scope module data_memory_tb $end
$scope module my_data_memory $end
$var reg 8 Q \MEM_ARRAY[27] [7:0] $end
$upscope $end
$upscope $end
$scope module data_memory_tb $end
$scope module my_data_memory $end
$var reg 8 R \MEM_ARRAY[28] [7:0] $end
$upscope $end
$upscope $end
$scope module data_memory_tb $end
$scope module my_data_memory $end
$var reg 8 S \MEM_ARRAY[29] [7:0] $end
$upscope $end
$upscope $end
$scope module data_memory_tb $end
$scope module my_data_memory $end
$var reg 8 T \MEM_ARRAY[30] [7:0] $end
$upscope $end
$upscope $end
$scope module data_memory_tb $end
$scope module my_data_memory $end
$var reg 8 U \MEM_ARRAY[31] [7:0] $end
$upscope $end
$upscope $end
$scope module data_memory_tb $end
$scope module my_data_memory $end
$var reg 8 V \MEM_ARRAY[32] [7:0] $end
$upscope $end
$upscope $end
$scope module data_memory_tb $end
$scope module my_data_memory $end
$var reg 8 W \MEM_ARRAY[33] [7:0] $end
$upscope $end
$upscope $end
$scope module data_memory_tb $end
$scope module my_data_memory $end
$var reg 8 X \MEM_ARRAY[34] [7:0] $end
$upscope $end
$upscope $end
$scope module data_memory_tb $end
$scope module my_data_memory $end
$var reg 8 Y \MEM_ARRAY[35] [7:0] $end
$upscope $end
$upscope $end
$scope module data_memory_tb $end
$scope module my_data_memory $end
$var reg 8 Z \MEM_ARRAY[36] [7:0] $end
$upscope $end
$upscope $end
$scope module data_memory_tb $end
$scope module my_data_memory $end
$var reg 8 [ \MEM_ARRAY[37] [7:0] $end
$upscope $end
$upscope $end
$scope module data_memory_tb $end
$scope module my_data_memory $end
$var reg 8 \ \MEM_ARRAY[38] [7:0] $end
$upscope $end
$upscope $end
$scope module data_memory_tb $end
$scope module my_data_memory $end
$var reg 8 ] \MEM_ARRAY[39] [7:0] $end
$upscope $end
$upscope $end
$scope module data_memory_tb $end
$scope module my_data_memory $end
$var reg 8 ^ \MEM_ARRAY[40] [7:0] $end
$upscope $end
$upscope $end
$scope module data_memory_tb $end
$scope module my_data_memory $end
$var reg 8 _ \MEM_ARRAY[41] [7:0] $end
$upscope $end
$upscope $end
$scope module data_memory_tb $end
$scope module my_data_memory $end
$var reg 8 ` \MEM_ARRAY[42] [7:0] $end
$upscope $end
$upscope $end
$scope module data_memory_tb $end
$scope module my_data_memory $end
$var reg 8 a \MEM_ARRAY[43] [7:0] $end
$upscope $end
$upscope $end
$scope module data_memory_tb $end
$scope module my_data_memory $end
$var reg 8 b \MEM_ARRAY[44] [7:0] $end
$upscope $end
$upscope $end
$scope module data_memory_tb $end
$scope module my_data_memory $end
$var reg 8 c \MEM_ARRAY[45] [7:0] $end
$upscope $end
$upscope $end
$scope module data_memory_tb $end
$scope module my_data_memory $end
$var reg 8 d \MEM_ARRAY[46] [7:0] $end
$upscope $end
$upscope $end
$scope module data_memory_tb $end
$scope module my_data_memory $end
$var reg 8 e \MEM_ARRAY[47] [7:0] $end
$upscope $end
$upscope $end
$scope module data_memory_tb $end
$scope module my_data_memory $end
$var reg 8 f \MEM_ARRAY[48] [7:0] $end
$upscope $end
$upscope $end
$scope module data_memory_tb $end
$scope module my_data_memory $end
$var reg 8 g \MEM_ARRAY[49] [7:0] $end
$upscope $end
$upscope $end
$scope module data_memory_tb $end
$scope module my_data_memory $end
$var reg 8 h \MEM_ARRAY[50] [7:0] $end
$upscope $end
$upscope $end
$scope module data_memory_tb $end
$scope module my_data_memory $end
$var reg 8 i \MEM_ARRAY[51] [7:0] $end
$upscope $end
$upscope $end
$scope module data_memory_tb $end
$scope module my_data_memory $end
$var reg 8 j \MEM_ARRAY[52] [7:0] $end
$upscope $end
$upscope $end
$scope module data_memory_tb $end
$scope module my_data_memory $end
$var reg 8 k \MEM_ARRAY[53] [7:0] $end
$upscope $end
$upscope $end
$scope module data_memory_tb $end
$scope module my_data_memory $end
$var reg 8 l \MEM_ARRAY[54] [7:0] $end
$upscope $end
$upscope $end
$scope module data_memory_tb $end
$scope module my_data_memory $end
$var reg 8 m \MEM_ARRAY[55] [7:0] $end
$upscope $end
$upscope $end
$scope module data_memory_tb $end
$scope module my_data_memory $end
$var reg 8 n \MEM_ARRAY[56] [7:0] $end
$upscope $end
$upscope $end
$scope module data_memory_tb $end
$scope module my_data_memory $end
$var reg 8 o \MEM_ARRAY[57] [7:0] $end
$upscope $end
$upscope $end
$scope module data_memory_tb $end
$scope module my_data_memory $end
$var reg 8 p \MEM_ARRAY[58] [7:0] $end
$upscope $end
$upscope $end
$scope module data_memory_tb $end
$scope module my_data_memory $end
$var reg 8 q \MEM_ARRAY[59] [7:0] $end
$upscope $end
$upscope $end
$scope module data_memory_tb $end
$scope module my_data_memory $end
$var reg 8 r \MEM_ARRAY[60] [7:0] $end
$upscope $end
$upscope $end
$scope module data_memory_tb $end
$scope module my_data_memory $end
$var reg 8 s \MEM_ARRAY[61] [7:0] $end
$upscope $end
$upscope $end
$scope module data_memory_tb $end
$scope module my_data_memory $end
$var reg 8 t \MEM_ARRAY[62] [7:0] $end
$upscope $end
$upscope $end
$scope module data_memory_tb $end
$scope module my_data_memory $end
$var reg 8 u \MEM_ARRAY[63] [7:0] $end
$upscope $end
$upscope $end
$scope module data_memory_tb $end
$scope module my_data_memory $end
$var reg 8 v \MEM_ARRAY[64] [7:0] $end
$upscope $end
$upscope $end
$scope module data_memory_tb $end
$scope module my_data_memory $end
$var reg 8 w \MEM_ARRAY[65] [7:0] $end
$upscope $end
$upscope $end
$scope module data_memory_tb $end
$scope module my_data_memory $end
$var reg 8 x \MEM_ARRAY[66] [7:0] $end
$upscope $end
$upscope $end
$scope module data_memory_tb $end
$scope module my_data_memory $end
$var reg 8 y \MEM_ARRAY[67] [7:0] $end
$upscope $end
$upscope $end
$scope module data_memory_tb $end
$scope module my_data_memory $end
$var reg 8 z \MEM_ARRAY[68] [7:0] $end
$upscope $end
$upscope $end
$scope module data_memory_tb $end
$scope module my_data_memory $end
$var reg 8 { \MEM_ARRAY[69] [7:0] $end
$upscope $end
$upscope $end
$scope module data_memory_tb $end
$scope module my_data_memory $end
$var reg 8 | \MEM_ARRAY[70] [7:0] $end
$upscope $end
$upscope $end
$scope module data_memory_tb $end
$scope module my_data_memory $end
$var reg 8 } \MEM_ARRAY[71] [7:0] $end
$upscope $end
$upscope $end
$scope module data_memory_tb $end
$scope module my_data_memory $end
$var reg 8 ~ \MEM_ARRAY[72] [7:0] $end
$upscope $end
$upscope $end
$scope module data_memory_tb $end
$scope module my_data_memory $end
$var reg 8 !" \MEM_ARRAY[73] [7:0] $end
$upscope $end
$upscope $end
$scope module data_memory_tb $end
$scope module my_data_memory $end
$var reg 8 "" \MEM_ARRAY[74] [7:0] $end
$upscope $end
$upscope $end
$scope module data_memory_tb $end
$scope module my_data_memory $end
$var reg 8 #" \MEM_ARRAY[75] [7:0] $end
$upscope $end
$upscope $end
$scope module data_memory_tb $end
$scope module my_data_memory $end
$var reg 8 $" \MEM_ARRAY[76] [7:0] $end
$upscope $end
$upscope $end
$scope module data_memory_tb $end
$scope module my_data_memory $end
$var reg 8 %" \MEM_ARRAY[77] [7:0] $end
$upscope $end
$upscope $end
$scope module data_memory_tb $end
$scope module my_data_memory $end
$var reg 8 &" \MEM_ARRAY[78] [7:0] $end
$upscope $end
$upscope $end
$scope module data_memory_tb $end
$scope module my_data_memory $end
$var reg 8 '" \MEM_ARRAY[79] [7:0] $end
$upscope $end
$upscope $end
$scope module data_memory_tb $end
$scope module my_data_memory $end
$var reg 8 (" \MEM_ARRAY[80] [7:0] $end
$upscope $end
$upscope $end
$scope module data_memory_tb $end
$scope module my_data_memory $end
$var reg 8 )" \MEM_ARRAY[81] [7:0] $end
$upscope $end
$upscope $end
$scope module data_memory_tb $end
$scope module my_data_memory $end
$var reg 8 *" \MEM_ARRAY[82] [7:0] $end
$upscope $end
$upscope $end
$scope module data_memory_tb $end
$scope module my_data_memory $end
$var reg 8 +" \MEM_ARRAY[83] [7:0] $end
$upscope $end
$upscope $end
$scope module data_memory_tb $end
$scope module my_data_memory $end
$var reg 8 ," \MEM_ARRAY[84] [7:0] $end
$upscope $end
$upscope $end
$scope module data_memory_tb $end
$scope module my_data_memory $end
$var reg 8 -" \MEM_ARRAY[85] [7:0] $end
$upscope $end
$upscope $end
$scope module data_memory_tb $end
$scope module my_data_memory $end
$var reg 8 ." \MEM_ARRAY[86] [7:0] $end
$upscope $end
$upscope $end
$scope module data_memory_tb $end
$scope module my_data_memory $end
$var reg 8 /" \MEM_ARRAY[87] [7:0] $end
$upscope $end
$upscope $end
$scope module data_memory_tb $end
$scope module my_data_memory $end
$var reg 8 0" \MEM_ARRAY[88] [7:0] $end
$upscope $end
$upscope $end
$scope module data_memory_tb $end
$scope module my_data_memory $end
$var reg 8 1" \MEM_ARRAY[89] [7:0] $end
$upscope $end
$upscope $end
$scope module data_memory_tb $end
$scope module my_data_memory $end
$var reg 8 2" \MEM_ARRAY[90] [7:0] $end
$upscope $end
$upscope $end
$scope module data_memory_tb $end
$scope module my_data_memory $end
$var reg 8 3" \MEM_ARRAY[91] [7:0] $end
$upscope $end
$upscope $end
$scope module data_memory_tb $end
$scope module my_data_memory $end
$var reg 8 4" \MEM_ARRAY[92] [7:0] $end
$upscope $end
$upscope $end
$scope module data_memory_tb $end
$scope module my_data_memory $end
$var reg 8 5" \MEM_ARRAY[93] [7:0] $end
$upscope $end
$upscope $end
$scope module data_memory_tb $end
$scope module my_data_memory $end
$var reg 8 6" \MEM_ARRAY[94] [7:0] $end
$upscope $end
$upscope $end
$scope module data_memory_tb $end
$scope module my_data_memory $end
$var reg 8 7" \MEM_ARRAY[95] [7:0] $end
$upscope $end
$upscope $end
$scope module data_memory_tb $end
$scope module my_data_memory $end
$var reg 8 8" \MEM_ARRAY[96] [7:0] $end
$upscope $end
$upscope $end
$scope module data_memory_tb $end
$scope module my_data_memory $end
$var reg 8 9" \MEM_ARRAY[97] [7:0] $end
$upscope $end
$upscope $end
$scope module data_memory_tb $end
$scope module my_data_memory $end
$var reg 8 :" \MEM_ARRAY[98] [7:0] $end
$upscope $end
$upscope $end
$scope module data_memory_tb $end
$scope module my_data_memory $end
$var reg 8 ;" \MEM_ARRAY[99] [7:0] $end
$upscope $end
$upscope $end
$enddefinitions $end
$comment Show the parameter values. $end
$dumpall
$end
#0
$dumpvars
bx ;"
bx :"
bx 9"
bx 8"
bx 7"
bx 6"
bx 5"
bx 4"
bx 3"
bx 2"
bx 1"
bx 0"
bx /"
bx ."
bx -"
bx ,"
bx +"
bx *"
bx )"
bx ("
bx '"
bx &"
bx %"
bx $"
bx #"
bx ""
bx !"
bx ~
bx }
bx |
bx {
bx z
bx y
bx x
bx w
bx v
bx u
bx t
bx s
bx r
bx q
bx p
bx o
bx n
bx m
bx l
bx k
bx j
bx i
bx h
bx g
bx f
bx e
bx d
bx c
bx b
bx a
bx `
bx _
bx ^
bx ]
bx \
bx [
bx Z
bx Y
bx X
bx W
bx V
bx U
bx T
bx S
bx R
bx Q
bx P
bx O
bx N
bx M
bx L
bx K
bx J
bx I
bx H
bx G
bx F
bx E
bx D
bx C
bx B
bx A
bx @
bx ?
bx >
bx =
bx <
bx ;
bx :
bx 9
bx 8
bx 7
bx 6
bx 5
bx 4
bx 3
bx 2
b10010001101001010101111001101 1
b1111 0
0/
0.
0-
0,
0+
0*
bx )
b0 (
b1100100 '
b10010001101001010101111001101 &
0%
b1111 $
0#
b0 "
bx !
$end
#4
b10010001101001010101111001101 2
b1010101111001101 3
b0 !
b0 4
b10010 9
b110100 8
b10101011 7
b11001101 6
b11001101 )
1#
#5
b0 2
b0 3
b0 ;"
b0 :"
b0 9"
b0 8"
b0 7"
b0 6"
b0 5"
b0 4"
b0 3"
b0 2"
b0 1"
b0 0"
b0 /"
b0 ."
b0 -"
b0 ,"
b0 +"
b0 *"
b0 )"
b0 ("
b0 '"
b0 &"
b0 %"
b0 $"
b0 #"
b0 ""
b0 !"
b0 ~
b0 }
b0 |
b0 {
b0 z
b0 y
b0 x
b0 w
b0 v
b0 u
b0 t
b0 s
b0 r
b0 q
b0 p
b0 o
b0 n
b0 m
b0 l
b0 k
b0 j
b0 i
b0 h
b0 g
b0 f
b0 e
b0 d
b0 c
b0 b
b0 a
b0 `
b0 _
b0 ^
b0 ]
b0 \
b0 [
b0 Z
b0 Y
b0 X
b0 W
b0 V
b0 U
b0 T
b0 S
b0 R
b0 Q
b0 P
b0 O
b0 N
b0 M
b0 L
b0 K
b0 J
b0 I
b0 H
b0 G
b0 F
b0 E
b0 D
b0 C
b0 B
b0 A
b0 @
b0 ?
b0 >
b0 =
b0 <
b0 ;
b0 :
b0 9
b0 8
b0 7
b0 6
b0 )
b10000000000000000000 5
1%
#8
0#
#9
0%
#12
b10010001101001010101111001101 2
b1010101111001101 3
b10010 9
b110100 8
b10101011 7
b11001101 6
b11001101 )
1#
#16
0#
#19
1*
1/
b0 2
b0 3
b10101011110011010001001000110101 &
b10101011110011010001001000110101 1
b0 )
b100 "
b100 (
b1010 $
b1010 0
#20
1#
#24
0#
#28
1#
#29
b10010001101001010101111001101 2
b1010101111001101 3
b10101011110011010001001000110110 &
b10101011110011010001001000110110 1
b11001101 )
b0 "
b0 (
#32
0#
#36
b10010001101001010101111001101 !
b10010001101001010101111001101 4
1#
#39
1*
1+
0/
b10101011110011010001001000110011 &
b10101011110011010001001000110011 1
b1000 $
b1000 0
#40
0#
#44
b11111111111111111111111111001101 !
b11111111111111111111111111001101 4
1#
#48
0#
#49
1.
0+
0-
b10101011110011010001001000100100 &
b10101011110011010001001000100100 1
b1101 $
b1101 0
#52
b1010101111001101 !
b1010101111001101 4
1#
#56
0#
#59
0*
0,
0.
b0 2
b0 3
b110010001101000001001000110100 &
b110010001101000001001000110100 1
b0 )
b100 "
b100 (
b1110 $
b1110 0
#60
b1001000110100 2
b1001000110100 3
b10010 ;
b110100 :
b110100 )
b0 !
b0 4
1#
#64
0#
#68
b10010 ;
b110100 :
1#
#69
b0 2
b0 3
b0 )
b1000 "
b1000 (
b1111 $
b1111 0
#72
0#
#76
b110010001101000001001000110100 2
b1001000110100 3
b110010 A
b110100 @
b10010 ?
b110100 >
b110100 )
1#
#79
1*
1,
b110010001100110001001000110100 &
b110010001100110001001000110100 1
b1100 $
b1100 0
#80
0#
#84
b110100 !
b110100 4
1#
